camstream/__init__.py
camstream/camstream.py
camstream-0.0.1.dist-info/LICENSE
camstream-0.0.1.dist-info/METADATA
camstream-0.0.1.dist-info/WHEEL
camstream-0.0.1.dist-info/top_level.txt
camstream-0.0.1.dist-info/RECORD
