Metadata-Version: 2.1
Name: camstream
Version: 0.0.1
Summary: Simple Interface for Camera Streams in Python
Author: Aimar Abimayu Pratama
Author-email: <aimarabimanyu123@gmail.com>
Keywords: python,interface,stream,camera,opencv,tkinter
License-File: LICENSE
Requires-Dist: opencv-python
Requires-Dist: tk
Requires-Dist: Pillow
